{
  "id": "rvv-stage2-runtime-scalar-splat-store-route-closure",
  "name": "rvv-stage2-runtime-scalar-splat-store-route-closure",
  "title": "Stage2 RVV runtime scalar splat-store route repair/closure",
  "description": "",
  "status": "completed",
  "dev_type": null,
  "scope": "RVV Stage2 runtime scalar splat-store route",
  "package": null,
  "priority": "P2",
  "creator": "codex",
  "assignee": "codex",
  "createdAt": "2026-06-06",
  "completedAt": "2026-06-06",
  "branch": null,
  "base_branch": "main",
  "worktree_path": null,
  "commit": null,
  "pr_url": null,
  "subtasks": [],
  "children": [],
  "parent": null,
  "relatedFiles": [],
  "notes": "",
  "meta": {}
}