{
  "id": "05-30-stage2-rvv-segment2-route-family-owner-completion",
  "name": "05-30-stage2-rvv-segment2-route-family-owner-completion",
  "title": "Stage2 RVV segment2 route-family owner completion",
  "description": "Externalize segment2 route-family operand binding and provider-plan ownership from RVVEmitCRoutePlanning.cpp into RVVEmitCSegment2RouteFamilyPlanOwners, keeping central segment2 dispatch neutral and requiring representative plain/computed-mask segment2 cases to derive plan facts through the owner module with fail-closed unsupported/mismatch coverage.",
  "status": "completed",
  "dev_type": null,
  "scope": null,
  "package": null,
  "priority": "P2",
  "creator": "codex",
  "assignee": "codex",
  "createdAt": "2026-05-30",
  "completedAt": "2026-05-30",
  "branch": null,
  "base_branch": "main",
  "worktree_path": null,
  "commit": null,
  "pr_url": null,
  "subtasks": [],
  "children": [],
  "parent": null,
  "relatedFiles": [],
  "notes": "",
  "meta": {}
}