{
  "id": "06-02-stage2-rvv-segment2-deinterleave-unit-store-artifact-abi",
  "name": "06-02-stage2-rvv-segment2-deinterleave-unit-store-artifact-abi",
  "title": "Stage2 RVV segment2 deinterleave unit-store artifact ABI boundary",
  "description": "Bounded Stage 2 e2e artifact/runtime ABI module for one pre-realized segment2_deinterleave_unit_store selected body.",
  "status": "completed",
  "dev_type": null,
  "scope": null,
  "package": null,
  "priority": "P1",
  "creator": "codex",
  "assignee": "codex",
  "createdAt": "2026-06-02",
  "completedAt": "2026-06-02",
  "branch": null,
  "base_branch": "main",
  "worktree_path": null,
  "commit": null,
  "pr_url": null,
  "subtasks": [],
  "children": [],
  "parent": null,
  "relatedFiles": [],
  "notes": "",
  "meta": {}
}