{
  "id": "stage2-rvv-selected-body-realization-route-path-integration",
  "name": "stage2-rvv-selected-body-realization-route-path-integration",
  "title": "Stage2 RVV selected-body realization route-path integration",
  "description": "Integrate the RVV plugin-owned selected-body realization boundary into one production-active RVV route/planning/provider/EmitC path cluster, preserving common EmitC neutrality and fail-closed unsupported realization.",
  "status": "completed",
  "dev_type": null,
  "scope": null,
  "package": null,
  "priority": "P1",
  "creator": "codex",
  "assignee": "codex",
  "createdAt": "2026-05-24",
  "completedAt": "2026-05-24",
  "branch": null,
  "base_branch": "main",
  "worktree_path": null,
  "commit": null,
  "pr_url": null,
  "subtasks": [],
  "children": [],
  "parent": null,
  "relatedFiles": [],
  "notes": "",
  "meta": {}
}