{
  "id": "rvv-i32-vmul-frontend-dispatch-ssh-evidence",
  "name": "rvv-i32-vmul-frontend-dispatch-ssh-evidence",
  "title": "RVV i32-vmul frontend-to-dispatch ssh evidence slice",
  "description": "Close one bounded i32-vmul frontend/dispatch handoff with RVV selected artifact plus scalar fallback artifact and fresh ssh rvv self-check evidence.",
  "status": "completed",
  "dev_type": null,
  "scope": null,
  "package": null,
  "priority": "P1",
  "creator": "codex",
  "assignee": "codex",
  "createdAt": "2026-05-11",
  "completedAt": "2026-05-11",
  "branch": null,
  "base_branch": "main",
  "worktree_path": null,
  "commit": null,
  "pr_url": null,
  "subtasks": [],
  "children": [],
  "parent": null,
  "relatedFiles": [],
  "notes": "",
  "meta": {}
}