{
  "id": "stage2-rvv-indexed-movement-operand-binding",
  "name": "stage2-rvv-indexed-movement-operand-binding",
  "title": "Stage2 RVV indexed movement operand binding adoption",
  "description": "Adopt RVV plugin-owned RouteOperandBindingPlan for current active indexed gather/scatter movement routes without adding new Stage2 operation coverage.",
  "status": "completed",
  "dev_type": null,
  "scope": "rvv-indexed-movement-binding",
  "package": null,
  "priority": "P1",
  "creator": "codex",
  "assignee": "codex",
  "createdAt": "2026-05-21",
  "completedAt": "2026-05-21",
  "branch": null,
  "base_branch": "main",
  "worktree_path": null,
  "commit": null,
  "pr_url": null,
  "subtasks": [],
  "children": [],
  "parent": null,
  "relatedFiles": [],
  "notes": "Converted active indexed gather/scatter movement routes to RVVRouteOperandBindingPlan authority with focused structural, negative, generated-bundle, ssh rvv, active-authority, and check-tianchenrv evidence.",
  "meta": {}
}